pyramid_apispec/__init__.py
pyramid_apispec/exceptions.py
pyramid_apispec/helpers.py
pyramid_apispec/views.py
pyramid_apispec/static/index.html
pyramid_apispec/static/index_script_template.html
pyramid_apispec/static/oauth2-redirect.html
pyramid_apispec-0.5.0.dist-info/LICENSE
pyramid_apispec-0.5.0.dist-info/METADATA
pyramid_apispec-0.5.0.dist-info/WHEEL
pyramid_apispec-0.5.0.dist-info/top_level.txt
pyramid_apispec-0.5.0.dist-info/RECORD
