Metadata-Version: 2.1
Name: pyramid-apispec
Version: 0.5.0
Summary: Pyramid plugin for openapi spec generation 
Home-page: https://github.com/ergo/pyramid_apispec
Author: Marcin Lulek
Author-email: marcin@webreactor.eu
License: BSD
Keywords: pyramid apispec marshmallow rest restful
Platform: UNKNOWN
Classifier: Development Status :: 4 - Beta
Classifier: Intended Audience :: Developers
Classifier: Framework :: Pyramid
Classifier: Topic :: Internet :: WWW/HTTP
Classifier: Topic :: Software Development :: Libraries :: Python Modules
Classifier: License :: OSI Approved :: BSD License
Classifier: Programming Language :: Python :: 3
Classifier: Programming Language :: Python :: 3.6
Classifier: Programming Language :: Python :: 3.7
Classifier: Programming Language :: Python :: 3.8
Classifier: Programming Language :: Python :: 3.9
Provides-Extra: dev
Provides-Extra: demo
Provides-Extra: lint
License-File: LICENSE
